ovretl/__init__.py
ovretl/billings_utils/__init__.py
ovretl/billings_utils/add_billing_info.py
ovretl/billings_utils/tests/__init__.py
ovretl/billings_utils/tests/test_add_billing_info.py
ovretl/containers_utils/__init__.py
ovretl/containers_utils/calculate_entity_containers.py
ovretl/containers_utils/calculate_single_container_teus.py
ovretl/containers_utils/merge_propositions_with_containers.py
ovretl/containers_utils/merge_shipments_with_containers.py
ovretl/containers_utils/tests/__init__.py
ovretl/containers_utils/tests/test_calculate_entity_containers.py
ovretl/containers_utils/tests/test_calculate_single_container_teus.py
ovretl/containers_utils/tests/test_merge_with_shipments_containers_then_with_propositions_containers.py
ovretl/db_utils/__init__.py
ovretl/db_utils/execute_complex_insert.py
ovretl/db_utils/execute_complexe_update.py
ovretl/db_utils/execute_complexe_update_three_cols.py
ovretl/db_utils/execute_simple_insert.py
ovretl/db_utils/execute_simple_query.py
ovretl/db_utils/execute_simple_update.py
ovretl/db_utils/fetch_db_credentials.py
ovretl/db_utils/nan_to_null.py
ovretl/db_utils/select_from_table.py
ovretl/employees_utils/__init__.py
ovretl/employees_utils/find_shipment_employee_name.py
ovretl/employees_utils/join_employees_associations_to_employees_name.py
ovretl/employees_utils/tests/__init__.py
ovretl/employees_utils/tests/test_add_employees_to_shipments.py
ovretl/kronos_propositions_utils/__init__.py
ovretl/kronos_propositions_utils/add_missing_categories.py
ovretl/kronos_propositions_utils/match_kronos_propositions_and_shipments.py
ovretl/kronos_propositions_utils/tests/__init__.py
ovretl/kronos_propositions_utils/tests/test_kronos_propositions_missing_categories.py
ovretl/kronos_propositions_utils/tests/test_match_kronos_propositions_and_shipments.py
ovretl/loads_utils/__init__.py
ovretl/loads_utils/calculate_entity_loads.py
ovretl/loads_utils/calculate_single_load_total_quantities.py
ovretl/loads_utils/merge_propositions_with_loads.py
ovretl-6.2.5.dist-info/WHEEL
ovretl-6.2.5.dist-info/METADATA
ovretl-6.2.5.dist-info/RECORD
