Metadata-Version: 2.1
Name: ovretl
Version: 6.2.5
Summary: Python package for Ovrsea ETL
License: MIT
Author: nicolas67
Author-email: nicolas@ovrsea.com
Requires-Python: >=3.7.9,<4
Classifier: License :: OSI Approved :: MIT License
Classifier: Programming Language :: Python :: 3
Classifier: Programming Language :: Python :: 3.10
Classifier: Programming Language :: Python :: 3.8
Classifier: Programming Language :: Python :: 3.9
Requires-Dist: boto3 (==1.24.19)
Requires-Dist: botocore (==1.27.19)
Requires-Dist: more-itertools (==8.14.0)
Requires-Dist: pandas (==1.3.5)
Requires-Dist: psycopg2-binary (>=2.8.5,<3.0.0)
Requires-Dist: pytz (>=2022.1,<2023.0)
Requires-Dist: snapshottest (>=0.5.1,<0.6.0)
Requires-Dist: time-machine (==2.1.0)
